Compiled from "Request1.java"
public class com.tang.boot.beans.jackson.Request1 extends com.tang.boot.beans.jackson.RequestBasic1 {
  public com.tang.boot.beans.jackson.Request1();
    Code:
       0: aload_0
       1: invokespecial #1                  // Method com/tang/boot/beans/jackson/RequestBasic1."<init>":()V
       4: return

  public void setName(java.lang.String);
    Code:
       0: aload_0
       1: aload_1
       2: putfield      #2                  // Field name:Ljava/lang/String;
       5: return

  public java.lang.String getName();
    Code:
       0: aload_0
       1: getfield      #2                  // Field name:Ljava/lang/String;
       4: areturn
}
